usefulfunctions2/__init__.py
usefulfunctions2/cls.py
usefulfunctions2/example_clearScreen.py
usefulfunctions2/example_menu.py
usefulfunctions2/menu.py
usefulfunctions2-0.0.2.dist-info/METADATA
usefulfunctions2-0.0.2.dist-info/WHEEL
usefulfunctions2-0.0.2.dist-info/licenses/LICENSE
usefulfunctions2-0.0.2.dist-info/RECORD
